spec_test_generator/__init__.py
spec_test_generator/__main__.py
spec_test_generator/coverage.py
spec_test_generator/generator.py
spec_test_generator/gherkin.py
spec_test_generator/id_manager.py
spec_test_generator/impact.py
spec_test_generator/importers.py
spec_test_generator/models.py
spec_test_generator/output.py
spec_test_generator/parser.py
spec_test_generator-1.0.0.dist-info/METADATA
spec_test_generator-1.0.0.dist-info/WHEEL
spec_test_generator-1.0.0.dist-info/entry_points.txt
spec_test_generator-1.0.0.dist-info/licenses/LICENSE
spec_test_generator-1.0.0.dist-info/RECORD
