Metadata-Version: 2.4
Name: spec-test-generator
Version: 1.0.0
Summary: Generate requirements and test artifacts from PRDs with stable IDs
Project-URL: Homepage, https://github.com/akz4ol/spec-test-generator-skill
Project-URL: Documentation, https://github.com/akz4ol/spec-test-generator-skill#readme
Project-URL: Repository, https://github.com/akz4ol/spec-test-generator-skill
Project-URL: Issues, https://github.com/akz4ol/spec-test-generator-skill/issues
Project-URL: Changelog, https://github.com/akz4ol/spec-test-generator-skill/blob/main/CHANGELOG.md
Author: Spec & Test Generator Skill Contributors
License-Expression: MIT
License-File: LICENSE
Keywords: prd,requirements,specification,test-generation,testing,traceability
Classifier: Development Status :: 4 - Beta
Classifier: Intended Audience :: Developers
Classifier: License :: OSI Approved :: MIT License
Classifier: Operating System :: OS Independent
Classifier: Programming Language :: Python :: 3
Classifier: Programming Language :: Python :: 3.10
Classifier: Programming Language :: Python :: 3.11
Classifier: Programming Language :: Python :: 3.12
Classifier: Topic :: Software Development :: Documentation
Classifier: Topic :: Software Development :: Quality Assurance
Classifier: Topic :: Software Development :: Testing
Requires-Python: >=3.10
Requires-Dist: jsonschema>=4.0
Requires-Dist: pyyaml>=6.0
Provides-Extra: dev
Requires-Dist: mypy>=1.0; extra == 'dev'
Requires-Dist: pytest-cov>=4.0; extra == 'dev'
Requires-Dist: pytest>=7.0; extra == 'dev'
Requires-Dist: ruff>=0.1.0; extra == 'dev'
Requires-Dist: types-pyyaml; extra == 'dev'
